baker.py
Baker-1.3.dist-info/METADATA
Baker-1.3.dist-info/DESCRIPTION.rst
Baker-1.3.dist-info/metadata.json
Baker-1.3.dist-info/top_level.txt
Baker-1.3.dist-info/RECORD
Baker-1.3.dist-info/WHEEL
