Metadata-Version: 1.1
Name: Baker
Version: 1.3
Summary: Easy, powerful access to Python functions from the command line
Home-page: http://bitbucket.org/mchaput/baker
Author: Michele Lacchia
Author-email: michelelacchia@gmail.com
License: Apache 2.0
Keywords: command line scripting
Platform: UNKNOWN
Classifier: Development Status :: 5 - Production/Stable
Classifier: Intended Audience :: Developers
Classifier: Intended Audience :: System Administrators
Classifier: Environment :: Console
Classifier: License :: OSI Approved :: Apache Software License
Classifier: Operating System :: OS Independent
Classifier: Programming Language :: Python
Classifier: Programming Language :: Python :: 2
Classifier: Programming Language :: Python :: 2.6
Classifier: Programming Language :: Python :: 2.7
Classifier: Programming Language :: Python :: 3
Classifier: Programming Language :: Python :: 3.2
